{
  "type": "ItemTurret",
  "targetAir": true,
  "targetGround": true,
  "health": 800,
  "size": 2,
  "inaccuracy": 2,
  "reloadTime": 1,
  "shots": 10,
  "recoilAmount": 10,
  "ammoUseEffect": "casing3",
  "shootSound": "drill",
  "shootCone": 25,
  "rotateSpeed": 5,
  "range": 40,
  "consumes": {
    "liquid": {
      "liquid": "water",
      "amount": 0.5,
      "booster": true
 }
},
 "ammoTypes": {
  "copper": {
    "speed": 10,
    "damage": 2,
   "ammoMultiplier": 1,
    "fragBullets": 4,
    "lifetime": 120,
   "hitSize": 8,
    "drawSize": 80,
    "collidesAir": false,
    "fragBullet": {
      "speed": 4,
      "damage": 10
    }
  },
  "graphite": {
    "speed": 10,
    "damage": 4,
    "ammoMultiplier": 1,
    "fragBullets": 30,
    "lifetime": 120,
    "hitSize": 8,
    "drawSize": 80,
    "collidesAir": false,
    "fragBullet": {
      "speed": 4,
     "damage": 2
    }
  },
  "coal": {
    "speed": 10,
    "damage": 1,
    "ammoMultiplier": 1,
    "fragBullets": 10,
    "lifetime": 120,
   "hitSize": 8,
    "drawSize": 80,
    "collidesAir": false,
    "incendAmount": 0.1,
    "incendSpread": 0.4,
    "incendChance": 0.7,
    "fragBullet": {
      "speed": 2,
      "damage": 2,
      "incendAmount": 0.1,
      "incendSpread": 0.1,
      "incendChance": 0.1
  }
},
 "requirements": [
  "copper/200",
  "lead/100",
  "graphite/100"
],
"category": "turret",
"research": "duo"
 
  }
}

